[
  {
    "id": 1,
    "costume_shop_type": 1,
    "costume_shop_group": 1,
    "product_id": 6001,
    "price_id": 500011,
    "price_count": 60
  },
  {
    "id": 2,
    "costume_shop_type": 28,
    "costume_shop_group": 201,
    "product_id": 6002,
    "price_id": 500011,
    "price_count": 90
  },
  {
    "id": 3,
    "costume_shop_type": 1,
    "costume_shop_group": 3,
    "product_id": 6003,
    "price_id": 500011,
    "price_count": 60
  },
  {
    "id": 4,
    "costume_shop_type": 1,
    "costume_shop_group": 4,
    "product_id": 6004,
    "price_id": 500011,
    "price_count": 60
  },
  {
    "id": 5,
    "costume_shop_type": 28,
    "costume_shop_group": 202,
    "product_id": 6005,
    "price_id": 500011,
    "price_count": 90
  },
  {
    "id": 6,
    "costume_shop_type": 28,
    "costume_shop_group": 203,
    "product_id": 6006,
    "price_id": 500011,
    "price_count": 90
  },
  {
    "id": 7,
    "costume_shop_type": 28,
    "costume_shop_group": 204,
    "product_id": 6007,
    "price_id": 500011,
    "price_count": 90
  },
  {
    "id": 8,
    "costume_shop_type": 1,
    "costume_shop_group": 8,
    "product_id": 6008,
    "price_id": 500011,
    "price_count": 60
  },
  {
    "id": 9,
    "costume_shop_type": 1,
    "costume_shop_group": 9,
    "product_id": 6009,
    "price_id": 500011,
    "price_count": 60
  },
  {
    "id": 10,
    "costume_shop_type": 1,
    "costume_shop_group": 10,
    "product_id": 6010,
    "price_id": 500011,
    "price_count": 60
  },
  {
    "id": 11,
    "costume_shop_type": 1,
    "costume_shop_group": 11,
    "product_id": 6011,
    "price_id": 500011,
    "price_count": 60
  },
  {
    "id": 12,
    "costume_shop_type": 1,
    "costume_shop_group": 12,
    "product_id": 6012,
    "price_id": 500011,
    "price_count": 60
  },
  {
    "id": 13,
    "costume_shop_type": 3,
    "costume_shop_group": 102,
    "product_id": 6021,
    "price_id": 500011,
    "price_count": 60
  },
  {
    "id": 14,
    "costume_shop_type": 3,
    "costume_shop_group": 101,
    "product_id": 6022,
    "price_id": 500011,
    "price_count": 90
  },
  {
    "id": 15,
    "costume_shop_type": 3,
    "costume_shop_group": 103,
    "product_id": 6023,
    "price_id": 500011,
    "price_count": 90
  },
  {
    "id": 16,
    "costume_shop_type": 5,
    "costume_shop_group": 215,
    "product_id": 6031,
    "price_id": 500011,
    "price_count": 90
  },
  {
    "id": 17,
    "costume_shop_type": 5,
    "costume_shop_group": 216,
    "product_id": 6032,
    "price_id": 500011,
    "price_count": 90
  },
  {
    "id": 18,
    "costume_shop_type": 5,
    "costume_shop_group": 217,
    "product_id": 6033,
    "price_id": 500011,
    "price_count": 90
  },
  {
    "id": 19,
    "costume_shop_type": 5,
    "costume_shop_group": 218,
    "product_id": 6034,
    "price_id": 500011,
    "price_count": 90
  },
  {
    "id": 20,
    "costume_shop_type": 5,
    "costume_shop_group": 219,
    "product_id": 6035,
    "price_id": 500011,
    "price_count": 90
  },
  {
    "id": 21,
    "costume_shop_type": 33,
    "costume_shop_group": 213,
    "product_id": 6036,
    "price_id": 500011,
    "price_count": 90
  },
  {
    "id": 22,
    "costume_shop_type": 33,
    "costume_shop_group": 214,
    "product_id": 6037,
    "price_id": 500011,
    "price_count": 90
  },
  {
    "id": 23,
    "costume_shop_type": 33,
    "costume_shop_group": 208,
    "product_id": 6038,
    "price_id": 500011,
    "price_count": 90
  },
  {
    "id": 24,
    "costume_shop_type": 6,
    "costume_shop_group": 33,
    "product_id": 6025,
    "price_id": 500011,
    "price_count": 60
  },
  {
    "id": 25,
    "costume_shop_type": 7,
    "costume_shop_group": 36,
    "product_id": 6051,
    "price_id": 500011,
    "price_count": 90
  },
  {
    "id": 26,
    "costume_shop_type": 8,
    "costume_shop_group": 39,
    "product_id": 6061,
    "price_id": 500011,
    "price_count": 90
  },
  {
    "id": 31,
    "costume_shop_type": 12,
    "costume_shop_group": 41,
    "product_id": 6062,
    "price_id": 500011,
    "price_count": 90
  },
  {
    "id": 32,
    "costume_shop_type": 12,
    "costume_shop_group": 42,
    "product_id": 6063,
    "price_id": 500011,
    "price_count": 90
  },
  {
    "id": 33,
    "costume_shop_type": 12,
    "costume_shop_group": 43,
    "product_id": 6064,
    "price_id": 500011,
    "price_count": 90
  },
  {
    "id": 34,
    "costume_shop_type": 12,
    "costume_shop_group": 44,
    "product_id": 6065,
    "price_id": 500011,
    "price_count": 60
  },
  {
    "id": 41,
    "costume_shop_type": 14,
    "costume_shop_group": 51,
    "product_id": 6041,
    "price_id": 500011,
    "price_count": 60
  },
  {
    "id": 42,
    "costume_shop_type": 14,
    "costume_shop_group": 52,
    "product_id": 6042,
    "price_id": 500011,
    "price_count": 60
  },
  {
    "id": 43,
    "costume_shop_type": 14,
    "costume_shop_group": 53,
    "product_id": 6043,
    "price_id": 500011,
    "price_count": 90
  },
  {
    "id": 44,
    "costume_shop_type": 14,
    "costume_shop_group": 54,
    "product_id": 6044,
    "price_id": 500011,
    "price_count": 90
  },
  {
    "id": 45,
    "costume_shop_type": 15,
    "costume_shop_group": 55,
    "product_id": 6045,
    "price_id": 500011,
    "price_count": 90
  },
  {
    "id": 46,
    "costume_shop_type": 15,
    "costume_shop_group": 56,
    "product_id": 6046,
    "price_id": 500011,
    "price_count": 90
  },
  {
    "id": 47,
    "costume_shop_type": 15,
    "costume_shop_group": 57,
    "product_id": 6047,
    "price_id": 500011,
    "price_count": 90
  },
  {
    "id": 48,
    "costume_shop_type": 15,
    "costume_shop_group": 58,
    "product_id": 6048,
    "price_id": 500011,
    "price_count": 90
  },
  {
    "id": 50,
    "costume_shop_type": 16,
    "costume_shop_group": 47,
    "product_id": 6066,
    "price_id": 500011,
    "price_count": 90
  },
  {
    "id": 51,
    "costume_shop_type": 18,
    "costume_shop_group": 59,
    "product_id": 6071,
    "price_id": 500011,
    "price_count": 60
  },
  {
    "id": 52,
    "costume_shop_type": 18,
    "costume_shop_group": 60,
    "product_id": 6072,
    "price_id": 500011,
    "price_count": 90
  },
  {
    "id": 53,
    "costume_shop_type": 18,
    "costume_shop_group": 61,
    "product_id": 6073,
    "price_id": 500011,
    "price_count": 90
  },
  {
    "id": 54,
    "costume_shop_type": 18,
    "costume_shop_group": 62,
    "product_id": 6074,
    "price_id": 500011,
    "price_count": 90
  },
  {
    "id": 55,
    "costume_shop_type": 18,
    "costume_shop_group": 63,
    "product_id": 6075,
    "price_id": 500011,
    "price_count": 90
  },
  {
    "id": 56,
    "costume_shop_type": 18,
    "costume_shop_group": 64,
    "product_id": 6076,
    "price_id": 500011,
    "price_count": 60
  },
  {
    "id": 57,
    "costume_shop_type": 19,
    "costume_shop_group": 65,
    "product_id": 6077,
    "price_id": 500011,
    "price_count": 90
  },
  {
    "id": 58,
    "costume_shop_type": 19,
    "costume_shop_group": 66,
    "product_id": 6078,
    "price_id": 500011,
    "price_count": 90
  },
  {
    "id": 59,
    "costume_shop_type": 19,
    "costume_shop_group": 67,
    "product_id": 6079,
    "price_id": 500011,
    "price_count": 90
  },
  {
    "id": 60,
    "costume_shop_type": 19,
    "costume_shop_group": 68,
    "product_id": 6080,
    "price_id": 500011,
    "price_count": 90
  },
  {
    "id": 61,
    "costume_shop_type": 19,
    "costume_shop_group": 69,
    "product_id": 6081,
    "price_id": 500011,
    "price_count": 90
  },
  {
    "id": 62,
    "costume_shop_type": 19,
    "costume_shop_group": 70,
    "product_id": 6082,
    "price_id": 500011,
    "price_count": 90
  },
  {
    "id": 63,
    "costume_shop_type": 20,
    "costume_shop_group": 71,
    "product_id": 6083,
    "price_id": 500011,
    "price_count": 90
  },
  {
    "id": 64,
    "costume_shop_type": 28,
    "costume_shop_group": 212,
    "product_id": 6084,
    "price_id": 500011,
    "price_count": 90
  },
  {
    "id": 65,
    "costume_shop_type": 20,
    "costume_shop_group": 73,
    "product_id": 6085,
    "price_id": 500011,
    "price_count": 90
  },
  {
    "id": 66,
    "costume_shop_type": 21,
    "costume_shop_group": 74,
    "product_id": 6091,
    "price_id": 500011,
    "price_count": 90
  },
  {
    "id": 67,
    "costume_shop_type": 21,
    "costume_shop_group": 75,
    "product_id": 6092,
    "price_id": 500011,
    "price_count": 90
  },
  {
    "id": 68,
    "costume_shop_type": 21,
    "costume_shop_group": 76,
    "product_id": 6093,
    "price_id": 500011,
    "price_count": 90
  },
  {
    "id": 69,
    "costume_shop_type": 22,
    "costume_shop_group": 77,
    "product_id": 6094,
    "price_id": 500011,
    "price_count": 90
  },
  {
    "id": 70,
    "costume_shop_type": 22,
    "costume_shop_group": 78,
    "product_id": 6095,
    "price_id": 500011,
    "price_count": 90
  },
  {
    "id": 71,
    "costume_shop_type": 22,
    "costume_shop_group": 79,
    "product_id": 6096,
    "price_id": 500011,
    "price_count": 90
  },
  {
    "id": 72,
    "costume_shop_type": 22,
    "costume_shop_group": 80,
    "product_id": 6097,
    "price_id": 500011,
    "price_count": 90
  },
  {
    "id": 73,
    "costume_shop_type": 25,
    "costume_shop_group": 83,
    "product_id": 6101,
    "price_id": 500011,
    "price_count": 90
  },
  {
    "id": 76,
    "costume_shop_type": 23,
    "costume_shop_group": 86,
    "product_id": 6102,
    "price_id": 500011,
    "price_count": 90
  },
  {
    "id": 77,
    "costume_shop_type": 24,
    "costume_shop_group": 89,
    "product_id": 6103,
    "price_id": 500011,
    "price_count": 90
  },
  {
    "id": 78,
    "costume_shop_type": 24,
    "costume_shop_group": 92,
    "product_id": 6104,
    "price_id": 500011,
    "price_count": 90
  },
  {
    "id": 79,
    "costume_shop_type": 26,
    "costume_shop_group": 94,
    "product_id": 6105,
    "price_id": 500011,
    "price_count": 90
  },
  {
    "id": 80,
    "costume_shop_type": 26,
    "costume_shop_group": 95,
    "product_id": 6106,
    "price_id": 500011,
    "price_count": 90
  },
  {
    "id": 81,
    "costume_shop_type": 27,
    "costume_shop_group": 98,
    "product_id": 6107,
    "price_id": 500011,
    "price_count": 90
  },
  {
    "id": 82,
    "costume_shop_type": 29,
    "costume_shop_group": 111,
    "product_id": 6108,
    "price_id": 500011,
    "price_count": 90
  },
  {
    "id": 83,
    "costume_shop_type": 30,
    "costume_shop_group": 112,
    "product_id": 6109,
    "price_id": 500011,
    "price_count": 90
  },
  {
    "id": 84,
    "costume_shop_type": 30,
    "costume_shop_group": 113,
    "product_id": 6110,
    "price_id": 500011,
    "price_count": 90
  },
  {
    "id": 85,
    "costume_shop_type": 30,
    "costume_shop_group": 114,
    "product_id": 6111,
    "price_id": 500011,
    "price_count": 90
  },
  {
    "id": 86,
    "costume_shop_type": 30,
    "costume_shop_group": 115,
    "product_id": 6112,
    "price_id": 500011,
    "price_count": 90
  },
  {
    "id": 87,
    "costume_shop_type": 31,
    "costume_shop_group": 116,
    "product_id": 6113,
    "price_id": 500011,
    "price_count": 90
  },
  {
    "id": 88,
    "costume_shop_type": 31,
    "costume_shop_group": 117,
    "product_id": 6114,
    "price_id": 500011,
    "price_count": 90
  },
  {
    "id": 89,
    "costume_shop_type": 32,
    "costume_shop_group": 120,
    "product_id": 6116,
    "price_id": 500011,
    "price_count": 90
  },
  {
    "id": 90,
    "costume_shop_type": 34,
    "costume_shop_group": 123,
    "product_id": 6117,
    "price_id": 500011,
    "price_count": 90
  },
  {
    "id": 91,
    "costume_shop_type": 35,
    "costume_shop_group": 126,
    "product_id": 6118,
    "price_id": 500011,
    "price_count": 90
  },
  {
    "id": 92,
    "costume_shop_type": 35,
    "costume_shop_group": 129,
    "product_id": 6119,
    "price_id": 500011,
    "price_count": 90
  },
  {
    "id": 93,
    "costume_shop_type": 36,
    "costume_shop_group": 132,
    "product_id": 6120,
    "price_id": 500011,
    "price_count": 90
  },
  {
    "id": 94,
    "costume_shop_type": 37,
    "costume_shop_group": 134,
    "product_id": 6121,
    "price_id": 500011,
    "price_count": 90
  },
  {
    "id": 95,
    "costume_shop_type": 37,
    "costume_shop_group": 136,
    "product_id": 6122,
    "price_id": 500011,
    "price_count": 90
  },
  {
    "id": 96,
    "costume_shop_type": 38,
    "costume_shop_group": 138,
    "product_id": 6126,
    "price_id": 500011,
    "price_count": 90
  },
  {
    "id": 97,
    "costume_shop_type": 38,
    "costume_shop_group": 139,
    "product_id": 6127,
    "price_id": 500011,
    "price_count": 90
  },
  {
    "id": 98,
    "costume_shop_type": 39,
    "costume_shop_group": 140,
    "product_id": 6123,
    "price_id": 500011,
    "price_count": 90
  },
  {
    "id": 99,
    "costume_shop_type": 39,
    "costume_shop_group": 141,
    "product_id": 6124,
    "price_id": 500011,
    "price_count": 90
  },
  {
    "id": 100,
    "costume_shop_type": 39,
    "costume_shop_group": 142,
    "product_id": 6125,
    "price_id": 500011,
    "price_count": 90
  },
  {
    "id": 102,
    "costume_shop_type": 40,
    "costume_shop_group": 145,
    "product_id": 6134,
    "price_id": 500011,
    "price_count": 90
  },
  {
    "id": 103,
    "costume_shop_type": 41,
    "costume_shop_group": 146,
    "product_id": 6128,
    "price_id": 500011,
    "price_count": 90
  },
  {
    "id": 104,
    "costume_shop_type": 41,
    "costume_shop_group": 147,
    "product_id": 6129,
    "price_id": 500011,
    "price_count": 90
  },
  {
    "id": 105,
    "costume_shop_type": 42,
    "costume_shop_group": 148,
    "product_id": 6130,
    "price_id": 500011,
    "price_count": 90
  },
  {
    "id": 106,
    "costume_shop_type": 42,
    "costume_shop_group": 149,
    "product_id": 6131,
    "price_id": 500011,
    "price_count": 90
  },
  {
    "id": 107,
    "costume_shop_type": 42,
    "costume_shop_group": 150,
    "product_id": 6132,
    "price_id": 500011,
    "price_count": 90
  },
  {
    "id": 108,
    "costume_shop_type": 44,
    "costume_shop_group": 152,
    "product_id": 6135,
    "price_id": 500011,
    "price_count": 90
  },
  {
    "id": 109,
    "costume_shop_type": 44,
    "costume_shop_group": 153,
    "product_id": 6136,
    "price_id": 500011,
    "price_count": 90
  },
  {
    "id": 110,
    "costume_shop_type": 43,
    "costume_shop_group": 155,
    "product_id": 6137,
    "price_id": 500011,
    "price_count": 90
  },
  {
    "id": 111,
    "costume_shop_type": 43,
    "costume_shop_group": 156,
    "product_id": 6138,
    "price_id": 500011,
    "price_count": 90
  },
  {
    "id": 112,
    "costume_shop_type": 45,
    "costume_shop_group": 158,
    "product_id": 6139,
    "price_id": 500011,
    "price_count": 90
  },
  {
    "id": 113,
    "costume_shop_type": 46,
    "costume_shop_group": 160,
    "product_id": 6140,
    "price_id": 500011,
    "price_count": 90
  },
  {
    "id": 114,
    "costume_shop_type": 46,
    "costume_shop_group": 161,
    "product_id": 6141,
    "price_id": 500011,
    "price_count": 90
  },
  {
    "id": 115,
    "costume_shop_type": 48,
    "costume_shop_group": 162,
    "product_id": 6142,
    "price_id": 500011,
    "price_count": 90
  },
  {
    "id": 116,
    "costume_shop_type": 48,
    "costume_shop_group": 163,
    "product_id": 6143,
    "price_id": 500011,
    "price_count": 90
  },
  {
    "id": 117,
    "costume_shop_type": 48,
    "costume_shop_group": 164,
    "product_id": 6144,
    "price_id": 500011,
    "price_count": 90
  },
  {
    "id": 118,
    "costume_shop_type": 49,
    "costume_shop_group": 166,
    "product_id": 6145,
    "price_id": 500011,
    "price_count": 90
  },
  {
    "id": 119,
    "costume_shop_type": 49,
    "costume_shop_group": 167,
    "product_id": 6146,
    "price_id": 500011,
    "price_count": 90
  }
]